mortm/__init__.py
mortm/constants.py
mortm/models/__init__.py
mortm/models/bertm.py
mortm/models/mortm.py
mortm/models/s_mrotm.py
mortm/models/v_mortm.py
mortm/models/modules/PositionalEncoding.py
mortm/models/modules/__init__.py
mortm/models/modules/attention.py
mortm/models/modules/audio_patch.py
mortm/models/modules/config.py
mortm/models/modules/layers.py
mortm/models/modules/progress.py
mortm/train/__init__.py
mortm/train/config.py
mortm/train/custom_token.py
mortm/train/datasets.py
mortm/train/epoch.py
mortm/train/noam.py
mortm/train/tokenizer.py
mortm/train/train.py
mortm/train/rl/__init__.py
mortm/train/rl/reinforcement.py
mortm/train/utils/__init__.py
mortm/train/utils/chord_midi.py
mortm/train/utils/loss.py
mortm/utils/__init__.py
mortm/utils/convert.py
mortm/utils/de_convert.py
mortm/utils/eval.py
mortm/utils/generate.py
mortm/utils/gmail_messanger.py
mortm/utils/messager.py
MORTM-4.1.33.dist-info/METADATA
MORTM-4.1.33.dist-info/WHEEL
MORTM-4.1.33.dist-info/top_level.txt
MORTM-4.1.33.dist-info/RECORD
