Metadata-Version: 2.1
Name: MORTM
Version: 4.1.33
Summary: 旋律生成、コード推定、マルチタスクな音楽生成を行うライブラリ
Home-page: https://github.com/Ayato964
Author: Nagoshi Takaaki
Author-email: nagoshi@kthrlab.jp
Classifier: Programming Language :: Python :: 3
Classifier: License :: OSI Approved :: MIT License
Classifier: Operating System :: OS Independent
Requires-Python: >=3.0
